{
    "$schema": "https://raw.githubusercontent.com/streetsidesoftware/cspell/main/cspell.schema.json",
    "version": "0.2",
    "language": "en",
    "words": [
        "creds",
        "datasource",
        "datasources",
        "direnv",
        "DOCKERHUB",
        "envrc",
        "fileignoreconfig",
        "goarch",
        "gochecknoglobals",
        "gocritic",
        "gofumpt",
        "golangci",
        "gomod",
        "goreleaser",
        "hadolint",
        "hashicorp",
        "incpatch",
        "ldflags",
        "markdownlint",
        "nolint",
        "opencontainers",
        "pastebin",
        "PKCS",
        "planmodifier",
        "providerserver",
        "stringplanmodifier",
        "tflog",
        "tfplugindocs",
        "tfprotov",
        "tfsdk",
        "thumbsup",
        "trimpath",
        "venv",
        "vesctl",
        "VOLTERRA",
        "wontfix",
        "workdir",
        "yamllint"
    ],
    "flagWords": [
        "hte"
    ],
    "ignorePaths": [
        ".devcontainer/devcontainer.json"
    ]
}
